fc_ims_zk.py
ran_zk-1.0.dist-info/METADATA
ran_zk-1.0.dist-info/WHEEL
ran_zk-1.0.dist-info/top_level.txt
ran_zk-1.0.dist-info/RECORD
