Metadata-Version: 2.1
Name: ran-zk
Version: 1.0
Summary: 大数据一班人
Home-page: UNKNOWN
Author: 大数据一班人
Author-email: fc@bigdata.com
License: UNKNOWN
Platform: UNKNOWN
